kadaptest1/__init__.py
kadaptest1/data.py
kadaptest1/first/__init__.py
kadaptest1/first/app.py
kadaptest1-0.0.1.dist-info/LICENSE
kadaptest1-0.0.1.dist-info/METADATA
kadaptest1-0.0.1.dist-info/WHEEL
kadaptest1-0.0.1.dist-info/top_level.txt
kadaptest1-0.0.1.dist-info/RECORD
